[{"count":6,"maximum":430,"percent":1,"queue":0,"timestamp":"2021-11-03T00:19:19.000Z"},{"count":6,"maximum":430,"percent":1,"queue":0,"timestamp":"2021-11-03T00:34:53.000Z"},{"count":6,"maximum":430,"percent":1,"queue":0,"timestamp":"2021-11-03T00:47:18.000Z"},{"count":6,"maximum":430,"percent":1,"queue":0,"timestamp":"2021-11-03T00:59:49.000Z"},{"count":6,"maximum":430,"percent":1,"queue":0,"timestamp":"2021-11-03T02:14:13.000Z"},{"count":6,"maximum":430,"percent":1,"queue":0,"timestamp":"2021-11-03T03:07:27.000Z"},{"count":6,"maximum":430,"percent":1,"queue":0,"timestamp":"2021-11-03T03:38:32.000Z"},{"count":6,"maximum":430,"percent":1,"queue":0,"timestamp":"2021-11-03T03:53:07.000Z"},{"count":0,"maximum":430,"percent":0,"queue":0,"timestamp":"2021-11-03T04:15:30.000Z"},{"count":0,"maximum":430,"percent":0,"queue":0,"timestamp":"2021-11-03T04:34:09.000Z"},{"count":0,"maximum":430,"percent":0,"queue":0,"timestamp":"2021-11-03T04:47:23.000Z"},{"count":0,"maximum":430,"percent":0,"queue":0,"timestamp":"2021-11-03T04:59:32.000Z"},{"count":0,"maximum":430,"percent":0,"queue":0,"timestamp":"2021-11-03T05:31:50.000Z"},{"count":0,"maximum":430,"percent":0,"queue":0,"timestamp":"2021-11-03T05:53:56.000Z"},{"count":0,"maximum":430,"percent":0,"queue":0,"timestamp":"2021-11-03T06:14:51.000Z"},{"count":0,"maximum":430,"percent":0,"queue":0,"timestamp":"2021-11-03T06:29:47.000Z"},{"count":0,"maximum":430,"percent":0,"queue":0,"timestamp":"2021-11-03T06:42:00.000Z"},{"count":0,"maximum":430,"percent":0,"queue":0,"timestamp":"2021-11-03T06:54:16.000Z"},{"count":0,"maximum":430,"percent":0,"queue":0,"timestamp":"2021-11-03T07:20:46.000Z"},{"count":17,"maximum":430,"percent":4,"queue":0,"timestamp":"2021-11-03T07:42:57.000Z"},{"count":23,"maximum":430,"percent":5,"queue":0,"timestamp":"2021-11-03T07:55:04.000Z"},{"count":26,"maximum":430,"percent":6,"queue":0,"timestamp":"2021-11-03T08:18:34.000Z"},{"count":24,"maximum":430,"percent":6,"queue":0,"timestamp":"2021-11-03T08:32:10.000Z"},{"count":28,"maximum":430,"percent":7,"queue":0,"timestamp":"2021-11-03T08:44:14.000Z"},{"count":26,"maximum":430,"percent":6,"queue":0,"timestamp":"2021-11-03T08:56:37.000Z"},{"count":29,"maximum":430,"percent":7,"queue":0,"timestamp":"2021-11-03T09:26:25.000Z"},{"count":40,"maximum":430,"percent":9,"queue":0,"timestamp":"2021-11-03T09:44:45.000Z"},{"count":56,"maximum":430,"percent":13,"queue":0,"timestamp":"2021-11-03T09:56:59.000Z"},{"count":65,"maximum":430,"percent":15,"queue":0,"timestamp":"2021-11-03T10:22:33.000Z"},{"count":84,"maximum":430,"percent":20,"queue":0,"timestamp":"2021-11-03T10:38:57.000Z"},{"count":85,"maximum":430,"percent":20,"queue":0,"timestamp":"2021-11-03T10:51:17.000Z"},{"count":110,"maximum":430,"percent":26,"queue":0,"timestamp":"2021-11-03T11:11:00.000Z"},{"count":122,"maximum":430,"percent":28,"queue":0,"timestamp":"2021-11-03T11:33:43.000Z"},{"count":136,"maximum":430,"percent":32,"queue":0,"timestamp":"2021-11-03T11:46:47.000Z"},{"count":144,"maximum":430,"percent":33,"queue":0,"timestamp":"2021-11-03T11:59:08.000Z"},{"count":152,"maximum":430,"percent":35,"queue":0,"timestamp":"2021-11-03T12:20:03.000Z"},{"count":149,"maximum":430,"percent":35,"queue":0,"timestamp":"2021-11-03T12:32:31.000Z"},{"count":144,"maximum":430,"percent":33,"queue":0,"timestamp":"2021-11-03T12:44:35.000Z"},{"count":153,"maximum":430,"percent":36,"queue":0,"timestamp":"2021-11-03T12:57:02.000Z"},{"count":141,"maximum":430,"percent":33,"queue":0,"timestamp":"2021-11-03T13:35:47.000Z"}]