[{"count":0,"maximum":300,"percent":0,"queue":0,"timestamp":"2021-09-16T00:21:29.000Z"},{"count":0,"maximum":300,"percent":0,"queue":0,"timestamp":"2021-09-16T00:36:53.000Z"},{"count":0,"maximum":300,"percent":0,"queue":0,"timestamp":"2021-09-16T00:49:15.000Z"},{"count":0,"maximum":300,"percent":0,"queue":0,"timestamp":"2021-09-16T01:04:36.000Z"},{"count":0,"maximum":300,"percent":0,"queue":0,"timestamp":"2021-09-16T01:25:58.000Z"},{"count":0,"maximum":300,"percent":0,"queue":0,"timestamp":"2021-09-16T01:39:54.000Z"},{"count":0,"maximum":300,"percent":0,"queue":0,"timestamp":"2021-09-16T01:52:00.000Z"},{"count":0,"maximum":300,"percent":0,"queue":0,"timestamp":"2021-09-16T02:40:27.000Z"},{"count":0,"maximum":300,"percent":0,"queue":0,"timestamp":"2021-09-16T03:49:51.000Z"},{"count":0,"maximum":300,"percent":0,"queue":0,"timestamp":"2021-09-16T04:24:00.000Z"},{"count":0,"maximum":300,"percent":0,"queue":0,"timestamp":"2021-09-16T04:47:39.000Z"},{"count":0,"maximum":300,"percent":0,"queue":0,"timestamp":"2021-09-16T04:59:49.000Z"},{"count":0,"maximum":300,"percent":0,"queue":0,"timestamp":"2021-09-16T05:24:22.000Z"},{"count":0,"maximum":300,"percent":0,"queue":0,"timestamp":"2021-09-16T05:40:56.000Z"},{"count":0,"maximum":300,"percent":0,"queue":0,"timestamp":"2021-09-16T05:53:06.000Z"},{"count":0,"maximum":300,"percent":0,"queue":0,"timestamp":"2021-09-16T06:17:29.000Z"},{"count":0,"maximum":300,"percent":0,"queue":0,"timestamp":"2021-09-16T06:42:43.000Z"},{"count":0,"maximum":300,"percent":0,"queue":0,"timestamp":"2021-09-16T06:56:58.000Z"},{"count":0,"maximum":300,"percent":0,"queue":0,"timestamp":"2021-09-16T07:19:38.000Z"},{"count":0,"maximum":300,"percent":0,"queue":0,"timestamp":"2021-09-16T07:31:46.000Z"},{"count":0,"maximum":300,"percent":0,"queue":0,"timestamp":"2021-09-16T07:44:05.000Z"},{"count":0,"maximum":300,"percent":0,"queue":0,"timestamp":"2021-09-16T07:56:34.000Z"},{"count":10,"maximum":300,"percent":3,"queue":0,"timestamp":"2021-09-16T08:25:38.000Z"},{"count":11,"maximum":300,"percent":4,"queue":0,"timestamp":"2021-09-16T08:48:12.000Z"},{"count":9,"maximum":300,"percent":3,"queue":0,"timestamp":"2021-09-16T09:00:18.000Z"},{"count":10,"maximum":300,"percent":3,"queue":0,"timestamp":"2021-09-16T09:22:16.000Z"},{"count":8,"maximum":300,"percent":3,"queue":0,"timestamp":"2021-09-16T09:35:03.000Z"},{"count":9,"maximum":300,"percent":3,"queue":0,"timestamp":"2021-09-16T09:47:15.000Z"}]