[{"count":0,"maximum":33,"percent":0,"queue":0,"timestamp":"2021-12-04T00:09:15.000Z"},{"count":0,"maximum":33,"percent":0,"queue":0,"timestamp":"2021-12-04T00:29:53.000Z"},{"count":0,"maximum":33,"percent":0,"queue":0,"timestamp":"2021-12-04T00:43:18.000Z"},{"count":0,"maximum":33,"percent":0,"queue":0,"timestamp":"2021-12-04T00:55:44.000Z"},{"count":0,"maximum":33,"percent":0,"queue":0,"timestamp":"2021-12-04T02:08:28.000Z"},{"count":0,"maximum":33,"percent":0,"queue":0,"timestamp":"2021-12-04T03:06:44.000Z"},{"count":0,"maximum":33,"percent":0,"queue":0,"timestamp":"2021-12-04T03:43:37.000Z"},{"count":0,"maximum":33,"percent":0,"queue":0,"timestamp":"2021-12-04T03:58:02.000Z"},{"count":0,"maximum":33,"percent":0,"queue":0,"timestamp":"2021-12-04T04:24:15.000Z"},{"count":0,"maximum":33,"percent":0,"queue":0,"timestamp":"2021-12-04T04:41:26.000Z"},{"count":0,"maximum":33,"percent":0,"queue":0,"timestamp":"2021-12-04T04:53:35.000Z"},{"count":0,"maximum":33,"percent":0,"queue":0,"timestamp":"2021-12-04T05:21:25.000Z"},{"count":0,"maximum":33,"percent":0,"queue":0,"timestamp":"2021-12-04T05:48:57.000Z"},{"count":0,"maximum":33,"percent":0,"queue":0,"timestamp":"2021-12-04T06:05:03.000Z"},{"count":0,"maximum":33,"percent":0,"queue":0,"timestamp":"2021-12-04T06:26:14.000Z"},{"count":0,"maximum":33,"percent":0,"queue":0,"timestamp":"2021-12-04T06:39:34.000Z"},{"count":0,"maximum":33,"percent":0,"queue":0,"timestamp":"2021-12-04T06:51:45.000Z"},{"count":0,"maximum":33,"percent":0,"queue":0,"timestamp":"2021-12-04T07:13:46.000Z"},{"count":0,"maximum":33,"percent":0,"queue":0,"timestamp":"2021-12-04T07:40:04.000Z"},{"count":0,"maximum":33,"percent":0,"queue":0,"timestamp":"2021-12-04T07:55:22.000Z"},{"count":0,"maximum":33,"percent":0,"queue":0,"timestamp":"2021-12-04T08:19:14.000Z"},{"count":0,"maximum":33,"percent":0,"queue":0,"timestamp":"2021-12-04T08:33:18.000Z"},{"count":0,"maximum":33,"percent":0,"queue":0,"timestamp":"2021-12-04T08:45:35.000Z"},{"count":0,"maximum":33,"percent":0,"queue":0,"timestamp":"2021-12-04T08:57:53.000Z"},{"count":2,"maximum":33,"percent":6,"queue":0,"timestamp":"2021-12-04T09:28:08.000Z"},{"count":2,"maximum":33,"percent":6,"queue":0,"timestamp":"2021-12-04T09:47:30.000Z"},{"count":4,"maximum":33,"percent":12,"queue":0,"timestamp":"2021-12-04T09:59:42.000Z"},{"count":9,"maximum":33,"percent":27,"queue":0,"timestamp":"2021-12-04T10:25:01.000Z"},{"count":10,"maximum":33,"percent":30,"queue":0,"timestamp":"2021-12-04T10:42:25.000Z"},{"count":10,"maximum":33,"percent":30,"queue":0,"timestamp":"2021-12-04T10:54:33.000Z"},{"count":12,"maximum":33,"percent":36,"queue":0,"timestamp":"2021-12-04T11:19:36.000Z"},{"count":16,"maximum":33,"percent":48,"queue":0,"timestamp":"2021-12-04T11:38:05.000Z"},{"count":22,"maximum":33,"percent":67,"queue":0,"timestamp":"2021-12-04T11:50:12.000Z"},{"count":24,"maximum":33,"percent":73,"queue":0,"timestamp":"2021-12-04T12:06:33.000Z"},{"count":22,"maximum":33,"percent":67,"queue":0,"timestamp":"2021-12-04T12:25:29.000Z"},{"count":22,"maximum":33,"percent":67,"queue":0,"timestamp":"2021-12-04T12:37:38.000Z"},{"count":21,"maximum":33,"percent":64,"queue":0,"timestamp":"2021-12-04T12:49:48.000Z"},{"count":27,"maximum":33,"percent":82,"queue":0,"timestamp":"2021-12-04T13:10:43.000Z"},{"count":27,"maximum":33,"percent":82,"queue":0,"timestamp":"2021-12-04T13:49:06.000Z"},{"count":29,"maximum":33,"percent":88,"queue":0,"timestamp":"2021-12-04T14:14:20.000Z"},{"count":32,"maximum":33,"percent":97,"queue":0,"timestamp":"2021-12-04T14:36:57.000Z"},{"count":32,"maximum":33,"percent":97,"queue":0,"timestamp":"2021-12-04T14:49:09.000Z"},{"count":32,"maximum":33,"percent":97,"queue":0,"timestamp":"2021-12-04T15:04:01.000Z"},{"count":30,"maximum":33,"percent":91,"queue":0,"timestamp":"2021-12-04T15:24:07.000Z"},{"count":28,"maximum":33,"percent":85,"queue":0,"timestamp":"2021-12-04T15:37:57.000Z"},{"count":27,"maximum":33,"percent":82,"queue":0,"timestamp":"2021-12-04T15:50:19.000Z"},{"count":28,"maximum":33,"percent":85,"queue":0,"timestamp":"2021-12-04T16:08:01.000Z"},{"count":29,"maximum":33,"percent":88,"queue":0,"timestamp":"2021-12-04T16:32:39.000Z"},{"count":30,"maximum":33,"percent":91,"queue":0,"timestamp":"2021-12-04T16:49:32.000Z"},{"count":27,"maximum":33,"percent":82,"queue":0,"timestamp":"2021-12-04T17:08:24.000Z"},{"count":25,"maximum":33,"percent":76,"queue":0,"timestamp":"2021-12-04T17:49:41.000Z"},{"count":22,"maximum":33,"percent":67,"queue":0,"timestamp":"2021-12-04T18:14:19.000Z"},{"count":28,"maximum":33,"percent":85,"queue":0,"timestamp":"2021-12-04T18:39:39.000Z"},{"count":32,"maximum":33,"percent":97,"queue":0,"timestamp":"2021-12-04T18:51:51.000Z"},{"count":33,"maximum":33,"percent":100,"queue":0,"timestamp":"2021-12-04T19:13:51.000Z"},{"count":31,"maximum":33,"percent":94,"queue":0,"timestamp":"2021-12-04T19:38:24.000Z"},{"count":30,"maximum":33,"percent":91,"queue":0,"timestamp":"2021-12-04T19:53:07.000Z"}]