[{"count":0,"maximum":33,"percent":0,"queue":0,"timestamp":"2022-01-08T00:06:34.000Z"},{"count":0,"maximum":33,"percent":0,"queue":0,"timestamp":"2022-01-08T00:29:27.000Z"},{"count":0,"maximum":33,"percent":0,"queue":0,"timestamp":"2022-01-08T00:44:29.000Z"},{"count":0,"maximum":33,"percent":0,"queue":0,"timestamp":"2022-01-08T00:56:39.000Z"},{"count":0,"maximum":33,"percent":0,"queue":0,"timestamp":"2022-01-08T02:17:39.000Z"},{"count":0,"maximum":33,"percent":0,"queue":0,"timestamp":"2022-01-08T03:15:12.000Z"},{"count":0,"maximum":33,"percent":0,"queue":0,"timestamp":"2022-01-08T03:53:00.000Z"},{"count":0,"maximum":33,"percent":0,"queue":0,"timestamp":"2022-01-08T04:17:09.000Z"},{"count":0,"maximum":33,"percent":0,"queue":0,"timestamp":"2022-01-08T04:37:29.000Z"},{"count":0,"maximum":33,"percent":0,"queue":0,"timestamp":"2022-01-08T04:50:44.000Z"},{"count":0,"maximum":33,"percent":0,"queue":0,"timestamp":"2022-01-08T05:12:10.000Z"},{"count":0,"maximum":33,"percent":0,"queue":0,"timestamp":"2022-01-08T05:45:23.000Z"},{"count":0,"maximum":33,"percent":0,"queue":0,"timestamp":"2022-01-08T06:03:01.000Z"},{"count":0,"maximum":33,"percent":0,"queue":0,"timestamp":"2022-01-08T06:26:26.000Z"},{"count":0,"maximum":33,"percent":0,"queue":0,"timestamp":"2022-01-08T06:40:37.000Z"},{"count":0,"maximum":33,"percent":0,"queue":0,"timestamp":"2022-01-08T06:52:55.000Z"},{"count":0,"maximum":33,"percent":0,"queue":0,"timestamp":"2022-01-08T07:17:58.000Z"},{"count":0,"maximum":33,"percent":0,"queue":0,"timestamp":"2022-01-08T07:42:38.000Z"},{"count":0,"maximum":33,"percent":0,"queue":0,"timestamp":"2022-01-08T07:56:49.000Z"},{"count":0,"maximum":33,"percent":0,"queue":0,"timestamp":"2022-01-08T08:21:40.000Z"},{"count":0,"maximum":33,"percent":0,"queue":0,"timestamp":"2022-01-08T08:35:54.000Z"},{"count":0,"maximum":33,"percent":0,"queue":0,"timestamp":"2022-01-08T08:48:21.000Z"},{"count":0,"maximum":33,"percent":0,"queue":0,"timestamp":"2022-01-08T09:01:31.000Z"},{"count":3,"maximum":33,"percent":9,"queue":0,"timestamp":"2022-01-08T09:31:17.000Z"},{"count":7,"maximum":33,"percent":21,"queue":0,"timestamp":"2022-01-08T09:50:01.000Z"},{"count":11,"maximum":33,"percent":33,"queue":0,"timestamp":"2022-01-08T10:07:42.000Z"},{"count":13,"maximum":33,"percent":39,"queue":0,"timestamp":"2022-01-08T10:30:17.000Z"},{"count":14,"maximum":33,"percent":42,"queue":0,"timestamp":"2022-01-08T10:45:11.000Z"},{"count":14,"maximum":33,"percent":42,"queue":0,"timestamp":"2022-01-08T10:57:37.000Z"},{"count":19,"maximum":33,"percent":58,"queue":0,"timestamp":"2022-01-08T11:25:54.000Z"},{"count":24,"maximum":33,"percent":73,"queue":0,"timestamp":"2022-01-08T11:44:19.000Z"},{"count":26,"maximum":33,"percent":79,"queue":0,"timestamp":"2022-01-08T11:56:32.000Z"},{"count":26,"maximum":33,"percent":79,"queue":0,"timestamp":"2022-01-08T12:18:36.000Z"},{"count":27,"maximum":33,"percent":82,"queue":0,"timestamp":"2022-01-08T12:31:11.000Z"},{"count":29,"maximum":33,"percent":88,"queue":0,"timestamp":"2022-01-08T12:43:23.000Z"},{"count":30,"maximum":33,"percent":91,"queue":0,"timestamp":"2022-01-08T12:55:37.000Z"},{"count":31,"maximum":33,"percent":94,"queue":0,"timestamp":"2022-01-08T13:34:21.000Z"},{"count":25,"maximum":33,"percent":76,"queue":0,"timestamp":"2022-01-08T14:04:29.000Z"}]