[{"count":177,"maximum":177,"percent":100,"queue":0,"timestamp":"2021-12-19T00:09:56.000Z"},{"count":177,"maximum":177,"percent":100,"queue":0,"timestamp":"2021-12-19T00:30:08.000Z"},{"count":177,"maximum":177,"percent":100,"queue":0,"timestamp":"2021-12-19T00:43:31.000Z"},{"count":177,"maximum":177,"percent":100,"queue":0,"timestamp":"2021-12-19T00:55:57.000Z"},{"count":177,"maximum":177,"percent":100,"queue":0,"timestamp":"2021-12-19T02:18:36.000Z"},{"count":177,"maximum":177,"percent":100,"queue":0,"timestamp":"2021-12-19T03:19:41.000Z"},{"count":177,"maximum":177,"percent":100,"queue":0,"timestamp":"2021-12-19T03:50:56.000Z"},{"count":177,"maximum":177,"percent":100,"queue":0,"timestamp":"2021-12-19T04:10:41.000Z"},{"count":177,"maximum":177,"percent":100,"queue":0,"timestamp":"2021-12-19T04:32:14.000Z"},{"count":177,"maximum":177,"percent":100,"queue":0,"timestamp":"2021-12-19T04:46:46.000Z"},{"count":177,"maximum":177,"percent":100,"queue":0,"timestamp":"2021-12-19T04:58:47.000Z"},{"count":177,"maximum":177,"percent":100,"queue":0,"timestamp":"2021-12-19T05:32:33.000Z"},{"count":177,"maximum":177,"percent":100,"queue":0,"timestamp":"2021-12-19T05:55:54.000Z"},{"count":177,"maximum":177,"percent":100,"queue":0,"timestamp":"2021-12-19T06:20:12.000Z"},{"count":177,"maximum":177,"percent":100,"queue":0,"timestamp":"2021-12-19T06:34:01.000Z"},{"count":177,"maximum":177,"percent":100,"queue":0,"timestamp":"2021-12-19T06:46:10.000Z"},{"count":177,"maximum":177,"percent":100,"queue":0,"timestamp":"2021-12-19T06:58:57.000Z"},{"count":177,"maximum":177,"percent":100,"queue":0,"timestamp":"2021-12-19T07:28:47.000Z"},{"count":177,"maximum":177,"percent":100,"queue":0,"timestamp":"2021-12-19T07:50:45.000Z"},{"count":176,"maximum":177,"percent":99,"queue":0,"timestamp":"2021-12-19T08:09:28.000Z"},{"count":176,"maximum":177,"percent":99,"queue":0,"timestamp":"2021-12-19T08:28:46.000Z"},{"count":173,"maximum":177,"percent":98,"queue":0,"timestamp":"2021-12-19T08:40:53.000Z"},{"count":171,"maximum":177,"percent":97,"queue":0,"timestamp":"2021-12-19T08:53:28.000Z"},{"count":167,"maximum":177,"percent":94,"queue":0,"timestamp":"2021-12-19T09:18:49.000Z"},{"count":162,"maximum":177,"percent":92,"queue":0,"timestamp":"2021-12-19T09:39:57.000Z"},{"count":160,"maximum":177,"percent":90,"queue":0,"timestamp":"2021-12-19T09:52:08.000Z"},{"count":155,"maximum":177,"percent":88,"queue":0,"timestamp":"2021-12-19T10:12:46.000Z"},{"count":151,"maximum":177,"percent":85,"queue":0,"timestamp":"2021-12-19T10:32:42.000Z"},{"count":146,"maximum":177,"percent":82,"queue":0,"timestamp":"2021-12-19T10:45:39.000Z"},{"count":146,"maximum":177,"percent":82,"queue":0,"timestamp":"2021-12-19T10:57:52.000Z"},{"count":145,"maximum":177,"percent":82,"queue":0,"timestamp":"2021-12-19T11:25:38.000Z"},{"count":142,"maximum":177,"percent":80,"queue":0,"timestamp":"2021-12-19T11:43:06.000Z"},{"count":142,"maximum":177,"percent":80,"queue":0,"timestamp":"2021-12-19T11:55:18.000Z"},{"count":141,"maximum":177,"percent":80,"queue":0,"timestamp":"2021-12-19T12:16:34.000Z"},{"count":140,"maximum":177,"percent":79,"queue":0,"timestamp":"2021-12-19T12:29:50.000Z"},{"count":143,"maximum":177,"percent":81,"queue":0,"timestamp":"2021-12-19T12:42:00.000Z"},{"count":144,"maximum":177,"percent":81,"queue":0,"timestamp":"2021-12-19T12:54:19.000Z"},{"count":144,"maximum":177,"percent":81,"queue":0,"timestamp":"2021-12-19T13:29:00.000Z"},{"count":145,"maximum":177,"percent":82,"queue":0,"timestamp":"2021-12-19T14:01:56.000Z"},{"count":145,"maximum":177,"percent":82,"queue":0,"timestamp":"2021-12-19T14:29:32.000Z"},{"count":149,"maximum":177,"percent":84,"queue":0,"timestamp":"2021-12-19T14:43:12.000Z"},{"count":151,"maximum":177,"percent":85,"queue":0,"timestamp":"2021-12-19T14:55:30.000Z"},{"count":156,"maximum":177,"percent":88,"queue":0,"timestamp":"2021-12-19T15:18:40.000Z"},{"count":154,"maximum":177,"percent":87,"queue":0,"timestamp":"2021-12-19T15:32:11.000Z"},{"count":154,"maximum":177,"percent":87,"queue":0,"timestamp":"2021-12-19T15:44:17.000Z"},{"count":154,"maximum":177,"percent":87,"queue":0,"timestamp":"2021-12-19T15:56:39.000Z"},{"count":156,"maximum":177,"percent":88,"queue":0,"timestamp":"2021-12-19T16:23:42.000Z"},{"count":158,"maximum":177,"percent":89,"queue":0,"timestamp":"2021-12-19T16:42:59.000Z"},{"count":157,"maximum":177,"percent":89,"queue":0,"timestamp":"2021-12-19T16:55:19.000Z"},{"count":153,"maximum":177,"percent":86,"queue":0,"timestamp":"2021-12-19T17:31:46.000Z"},{"count":152,"maximum":177,"percent":86,"queue":0,"timestamp":"2021-12-19T18:03:41.000Z"},{"count":155,"maximum":177,"percent":88,"queue":0,"timestamp":"2021-12-19T18:33:10.000Z"},{"count":158,"maximum":177,"percent":89,"queue":0,"timestamp":"2021-12-19T18:48:31.000Z"},{"count":157,"maximum":177,"percent":89,"queue":0,"timestamp":"2021-12-19T19:01:58.000Z"},{"count":159,"maximum":177,"percent":90,"queue":0,"timestamp":"2021-12-19T19:30:17.000Z"},{"count":134,"maximum":177,"percent":76,"queue":0,"timestamp":"2021-12-19T19:49:32.000Z"},{"count":156,"maximum":177,"percent":88,"queue":0,"timestamp":"2021-12-19T20:04:53.000Z"},{"count":157,"maximum":177,"percent":89,"queue":0,"timestamp":"2021-12-19T20:21:23.000Z"},{"count":158,"maximum":177,"percent":89,"queue":0,"timestamp":"2021-12-19T20:34:04.000Z"},{"count":159,"maximum":177,"percent":90,"queue":0,"timestamp":"2021-12-19T20:46:13.000Z"},{"count":160,"maximum":177,"percent":90,"queue":0,"timestamp":"2021-12-19T20:58:33.000Z"},{"count":161,"maximum":177,"percent":91,"queue":0,"timestamp":"2021-12-19T21:24:47.000Z"}]