[{"count":177,"maximum":177,"percent":100,"queue":0,"timestamp":"2022-03-05T00:12:48.000Z"},{"count":177,"maximum":177,"percent":100,"queue":0,"timestamp":"2022-03-05T00:30:51.000Z"},{"count":177,"maximum":177,"percent":100,"queue":0,"timestamp":"2022-03-05T00:43:01.000Z"},{"count":177,"maximum":177,"percent":100,"queue":0,"timestamp":"2022-03-05T00:55:25.000Z"},{"count":177,"maximum":177,"percent":100,"queue":0,"timestamp":"2022-03-05T02:19:52.000Z"},{"count":177,"maximum":177,"percent":100,"queue":0,"timestamp":"2022-03-05T03:20:37.000Z"},{"count":177,"maximum":177,"percent":100,"queue":0,"timestamp":"2022-03-05T03:49:56.000Z"},{"count":177,"maximum":177,"percent":100,"queue":0,"timestamp":"2022-03-05T04:07:57.000Z"},{"count":177,"maximum":177,"percent":100,"queue":0,"timestamp":"2022-03-05T04:29:30.000Z"},{"count":177,"maximum":177,"percent":100,"queue":0,"timestamp":"2022-03-05T04:43:21.000Z"},{"count":177,"maximum":177,"percent":100,"queue":0,"timestamp":"2022-03-05T04:55:24.000Z"},{"count":177,"maximum":177,"percent":100,"queue":0,"timestamp":"2022-03-05T05:26:16.000Z"},{"count":177,"maximum":177,"percent":100,"queue":0,"timestamp":"2022-03-05T05:48:30.000Z"},{"count":177,"maximum":177,"percent":100,"queue":0,"timestamp":"2022-03-05T06:01:57.000Z"},{"count":177,"maximum":177,"percent":100,"queue":0,"timestamp":"2022-03-05T06:22:04.000Z"},{"count":177,"maximum":177,"percent":100,"queue":0,"timestamp":"2022-03-05T06:34:57.000Z"},{"count":177,"maximum":177,"percent":100,"queue":0,"timestamp":"2022-03-05T06:47:12.000Z"},{"count":177,"maximum":177,"percent":100,"queue":0,"timestamp":"2022-03-05T06:59:19.000Z"},{"count":177,"maximum":177,"percent":100,"queue":0,"timestamp":"2022-03-05T07:28:22.000Z"},{"count":177,"maximum":177,"percent":100,"queue":0,"timestamp":"2022-03-05T07:47:24.000Z"},{"count":177,"maximum":177,"percent":100,"queue":0,"timestamp":"2022-03-05T07:59:41.000Z"},{"count":175,"maximum":177,"percent":99,"queue":0,"timestamp":"2022-03-05T08:22:00.000Z"},{"count":174,"maximum":177,"percent":98,"queue":0,"timestamp":"2022-03-05T08:34:16.000Z"},{"count":174,"maximum":177,"percent":98,"queue":0,"timestamp":"2022-03-05T08:46:41.000Z"},{"count":170,"maximum":177,"percent":96,"queue":0,"timestamp":"2022-03-05T08:58:50.000Z"},{"count":165,"maximum":177,"percent":93,"queue":0,"timestamp":"2022-03-05T09:26:50.000Z"},{"count":161,"maximum":177,"percent":91,"queue":0,"timestamp":"2022-03-05T09:43:12.000Z"},{"count":161,"maximum":177,"percent":91,"queue":0,"timestamp":"2022-03-05T09:55:28.000Z"},{"count":154,"maximum":177,"percent":87,"queue":0,"timestamp":"2022-03-05T10:18:35.000Z"},{"count":155,"maximum":177,"percent":88,"queue":0,"timestamp":"2022-03-05T10:32:02.000Z"},{"count":155,"maximum":177,"percent":88,"queue":0,"timestamp":"2022-03-05T10:44:08.000Z"},{"count":155,"maximum":177,"percent":88,"queue":0,"timestamp":"2022-03-05T10:56:43.000Z"},{"count":154,"maximum":177,"percent":87,"queue":0,"timestamp":"2022-03-05T11:23:51.000Z"},{"count":154,"maximum":177,"percent":87,"queue":0,"timestamp":"2022-03-05T11:39:11.000Z"},{"count":152,"maximum":177,"percent":86,"queue":0,"timestamp":"2022-03-05T11:51:29.000Z"},{"count":150,"maximum":177,"percent":85,"queue":0,"timestamp":"2022-03-05T12:10:25.000Z"},{"count":148,"maximum":177,"percent":84,"queue":0,"timestamp":"2022-03-05T12:28:09.000Z"},{"count":145,"maximum":177,"percent":82,"queue":0,"timestamp":"2022-03-05T12:40:16.000Z"},{"count":145,"maximum":177,"percent":82,"queue":0,"timestamp":"2022-03-05T12:52:25.000Z"},{"count":144,"maximum":177,"percent":81,"queue":0,"timestamp":"2022-03-05T13:20:43.000Z"},{"count":146,"maximum":177,"percent":82,"queue":0,"timestamp":"2022-03-05T13:51:02.000Z"},{"count":149,"maximum":177,"percent":84,"queue":0,"timestamp":"2022-03-05T14:13:14.000Z"},{"count":148,"maximum":177,"percent":84,"queue":0,"timestamp":"2022-03-05T14:30:52.000Z"},{"count":151,"maximum":177,"percent":85,"queue":0,"timestamp":"2022-03-05T14:43:04.000Z"},{"count":150,"maximum":177,"percent":85,"queue":0,"timestamp":"2022-03-05T14:55:28.000Z"},{"count":151,"maximum":177,"percent":85,"queue":0,"timestamp":"2022-03-05T15:18:38.000Z"},{"count":151,"maximum":177,"percent":85,"queue":0,"timestamp":"2022-03-05T15:31:07.000Z"},{"count":150,"maximum":177,"percent":85,"queue":0,"timestamp":"2022-03-05T15:43:29.000Z"},{"count":150,"maximum":177,"percent":85,"queue":0,"timestamp":"2022-03-05T15:55:42.000Z"},{"count":162,"maximum":177,"percent":92,"queue":0,"timestamp":"2022-03-05T16:20:59.000Z"},{"count":161,"maximum":177,"percent":91,"queue":0,"timestamp":"2022-03-05T16:37:29.000Z"},{"count":161,"maximum":177,"percent":91,"queue":0,"timestamp":"2022-03-05T16:49:34.000Z"},{"count":158,"maximum":177,"percent":89,"queue":0,"timestamp":"2022-03-05T17:08:31.000Z"},{"count":157,"maximum":177,"percent":89,"queue":0,"timestamp":"2022-03-05T17:42:47.000Z"},{"count":156,"maximum":177,"percent":88,"queue":0,"timestamp":"2022-03-05T17:59:54.000Z"}]