[{"count":0,"maximum":32,"percent":0,"queue":0,"timestamp":"2021-07-26T00:12:04.000Z"},{"count":0,"maximum":32,"percent":0,"queue":0,"timestamp":"2021-07-26T00:31:38.000Z"},{"count":0,"maximum":32,"percent":0,"queue":0,"timestamp":"2021-07-26T00:43:43.000Z"},{"count":0,"maximum":32,"percent":0,"queue":0,"timestamp":"2021-07-26T00:55:48.000Z"},{"count":0,"maximum":32,"percent":0,"queue":0,"timestamp":"2021-07-26T01:20:18.000Z"},{"count":0,"maximum":32,"percent":0,"queue":0,"timestamp":"2021-07-26T01:34:11.000Z"},{"count":0,"maximum":32,"percent":0,"queue":0,"timestamp":"2021-07-26T01:46:21.000Z"},{"count":0,"maximum":32,"percent":0,"queue":0,"timestamp":"2021-07-26T01:58:44.000Z"},{"count":0,"maximum":32,"percent":0,"queue":0,"timestamp":"2021-07-26T03:13:06.000Z"},{"count":0,"maximum":32,"percent":0,"queue":0,"timestamp":"2021-07-26T04:10:27.000Z"},{"count":0,"maximum":32,"percent":0,"queue":0,"timestamp":"2021-07-26T04:40:22.000Z"},{"count":0,"maximum":32,"percent":0,"queue":0,"timestamp":"2021-07-26T04:52:56.000Z"},{"count":0,"maximum":32,"percent":0,"queue":0,"timestamp":"2021-07-26T05:14:42.000Z"},{"count":0,"maximum":32,"percent":0,"queue":0,"timestamp":"2021-07-26T05:36:01.000Z"}]