[{"count":0,"maximum":55,"percent":0,"queue":0,"timestamp":"2021-09-03T00:22:47.000Z"},{"count":0,"maximum":55,"percent":0,"queue":0,"timestamp":"2021-09-03T00:38:57.000Z"},{"count":0,"maximum":55,"percent":0,"queue":0,"timestamp":"2021-09-03T00:51:33.000Z"},{"count":0,"maximum":55,"percent":0,"queue":0,"timestamp":"2021-09-03T01:10:45.000Z"},{"count":0,"maximum":55,"percent":0,"queue":0,"timestamp":"2021-09-03T01:29:46.000Z"},{"count":0,"maximum":55,"percent":0,"queue":0,"timestamp":"2021-09-03T01:42:18.000Z"},{"count":0,"maximum":55,"percent":0,"queue":0,"timestamp":"2021-09-03T01:54:44.000Z"},{"count":0,"maximum":55,"percent":0,"queue":0,"timestamp":"2021-09-03T02:56:56.000Z"},{"count":0,"maximum":55,"percent":0,"queue":0,"timestamp":"2021-09-03T04:00:41.000Z"},{"count":0,"maximum":55,"percent":0,"queue":0,"timestamp":"2021-09-03T04:33:00.000Z"},{"count":0,"maximum":55,"percent":0,"queue":0,"timestamp":"2021-09-03T04:48:38.000Z"},{"count":0,"maximum":55,"percent":0,"queue":0,"timestamp":"2021-09-03T05:02:10.000Z"},{"count":0,"maximum":55,"percent":0,"queue":0,"timestamp":"2021-09-03T05:26:02.000Z"},{"count":0,"maximum":55,"percent":0,"queue":0,"timestamp":"2021-09-03T05:43:10.000Z"},{"count":0,"maximum":55,"percent":0,"queue":0,"timestamp":"2021-09-03T05:55:16.000Z"},{"count":0,"maximum":55,"percent":0,"queue":0,"timestamp":"2021-09-03T06:25:29.000Z"},{"count":0,"maximum":55,"percent":0,"queue":0,"timestamp":"2021-09-03T06:52:06.000Z"},{"count":0,"maximum":55,"percent":0,"queue":0,"timestamp":"2021-09-03T07:10:26.000Z"},{"count":0,"maximum":55,"percent":0,"queue":0,"timestamp":"2021-09-03T07:26:54.000Z"},{"count":0,"maximum":55,"percent":0,"queue":0,"timestamp":"2021-09-03T07:39:12.000Z"},{"count":0,"maximum":55,"percent":0,"queue":0,"timestamp":"2021-09-03T07:51:19.000Z"},{"count":0,"maximum":55,"percent":0,"queue":0,"timestamp":"2021-09-03T08:11:54.000Z"},{"count":0,"maximum":55,"percent":0,"queue":0,"timestamp":"2021-09-03T08:38:18.000Z"},{"count":0,"maximum":55,"percent":0,"queue":0,"timestamp":"2021-09-03T08:54:08.000Z"},{"count":0,"maximum":55,"percent":0,"queue":0,"timestamp":"2021-09-03T09:15:59.000Z"},{"count":0,"maximum":55,"percent":0,"queue":0,"timestamp":"2021-09-03T09:30:22.000Z"},{"count":0,"maximum":55,"percent":0,"queue":0,"timestamp":"2021-09-03T09:42:35.000Z"},{"count":0,"maximum":55,"percent":0,"queue":0,"timestamp":"2021-09-03T09:54:53.000Z"},{"count":0,"maximum":55,"percent":0,"queue":0,"timestamp":"2021-09-03T10:20:45.000Z"},{"count":0,"maximum":55,"percent":0,"queue":0,"timestamp":"2021-09-03T10:38:44.000Z"},{"count":0,"maximum":55,"percent":0,"queue":0,"timestamp":"2021-09-03T10:50:58.000Z"},{"count":0,"maximum":55,"percent":0,"queue":0,"timestamp":"2021-09-03T11:09:11.000Z"},{"count":0,"maximum":55,"percent":0,"queue":0,"timestamp":"2021-09-03T11:29:09.000Z"},{"count":0,"maximum":55,"percent":0,"queue":0,"timestamp":"2021-09-03T11:43:27.000Z"},{"count":0,"maximum":55,"percent":0,"queue":0,"timestamp":"2021-09-03T11:55:39.000Z"},{"count":0,"maximum":55,"percent":0,"queue":0,"timestamp":"2021-09-03T12:22:40.000Z"},{"count":0,"maximum":55,"percent":0,"queue":0,"timestamp":"2021-09-03T12:39:52.000Z"},{"count":0,"maximum":55,"percent":0,"queue":0,"timestamp":"2021-09-03T12:52:10.000Z"},{"count":0,"maximum":55,"percent":0,"queue":0,"timestamp":"2021-09-03T13:09:42.000Z"},{"count":0,"maximum":55,"percent":0,"queue":0,"timestamp":"2021-09-03T13:25:26.000Z"},{"count":0,"maximum":55,"percent":0,"queue":0,"timestamp":"2021-09-03T13:37:44.000Z"},{"count":0,"maximum":55,"percent":0,"queue":0,"timestamp":"2021-09-03T13:49:54.000Z"},{"count":0,"maximum":55,"percent":0,"queue":0,"timestamp":"2021-09-03T14:10:10.000Z"},{"count":0,"maximum":55,"percent":0,"queue":0,"timestamp":"2021-09-03T14:47:49.000Z"},{"count":0,"maximum":55,"percent":0,"queue":0,"timestamp":"2021-09-03T15:10:53.000Z"},{"count":0,"maximum":55,"percent":0,"queue":0,"timestamp":"2021-09-03T15:32:46.000Z"},{"count":0,"maximum":55,"percent":0,"queue":0,"timestamp":"2021-09-03T15:44:54.000Z"},{"count":0,"maximum":55,"percent":0,"queue":0,"timestamp":"2021-09-03T15:57:16.000Z"},{"count":0,"maximum":55,"percent":0,"queue":0,"timestamp":"2021-09-03T16:20:01.000Z"},{"count":0,"maximum":55,"percent":0,"queue":0,"timestamp":"2021-09-03T16:33:10.000Z"},{"count":0,"maximum":55,"percent":0,"queue":0,"timestamp":"2021-09-03T16:45:41.000Z"}]