[{"count":6,"maximum":600,"percent":1,"queue":0,"timestamp":"2021-11-11T00:09:14.000Z"},{"count":6,"maximum":600,"percent":1,"queue":0,"timestamp":"2021-11-11T00:29:42.000Z"},{"count":6,"maximum":600,"percent":1,"queue":0,"timestamp":"2021-11-11T00:43:19.000Z"},{"count":6,"maximum":600,"percent":1,"queue":0,"timestamp":"2021-11-11T00:55:34.000Z"},{"count":6,"maximum":600,"percent":1,"queue":0,"timestamp":"2021-11-11T02:07:28.000Z"},{"count":6,"maximum":600,"percent":1,"queue":0,"timestamp":"2021-11-11T03:06:15.000Z"},{"count":6,"maximum":600,"percent":1,"queue":0,"timestamp":"2021-11-11T03:39:40.000Z"},{"count":6,"maximum":600,"percent":1,"queue":0,"timestamp":"2021-11-11T03:54:38.000Z"},{"count":0,"maximum":600,"percent":0,"queue":0,"timestamp":"2021-11-11T04:19:19.000Z"},{"count":0,"maximum":600,"percent":0,"queue":0,"timestamp":"2021-11-11T04:36:48.000Z"}]