[{"count":120,"maximum":120,"percent":100,"queue":0,"timestamp":"2022-03-17T00:23:21.000Z"},{"count":120,"maximum":120,"percent":100,"queue":0,"timestamp":"2022-03-17T00:37:53.000Z"},{"count":120,"maximum":120,"percent":100,"queue":0,"timestamp":"2022-03-17T00:50:02.000Z"},{"count":120,"maximum":120,"percent":100,"queue":0,"timestamp":"2022-03-17T01:35:07.000Z"},{"count":120,"maximum":120,"percent":100,"queue":0,"timestamp":"2022-03-17T03:03:06.000Z"},{"count":120,"maximum":120,"percent":100,"queue":0,"timestamp":"2022-03-17T03:47:38.000Z"},{"count":120,"maximum":120,"percent":100,"queue":0,"timestamp":"2022-03-17T04:04:27.000Z"},{"count":120,"maximum":120,"percent":100,"queue":0,"timestamp":"2022-03-17T04:29:07.000Z"},{"count":120,"maximum":120,"percent":100,"queue":0,"timestamp":"2022-03-17T04:44:20.000Z"},{"count":120,"maximum":120,"percent":100,"queue":0,"timestamp":"2022-03-17T04:56:31.000Z"},{"count":120,"maximum":120,"percent":100,"queue":0,"timestamp":"2022-03-17T05:29:32.000Z"},{"count":120,"maximum":120,"percent":100,"queue":0,"timestamp":"2022-03-17T05:50:53.000Z"},{"count":120,"maximum":120,"percent":100,"queue":0,"timestamp":"2022-03-17T06:09:47.000Z"},{"count":120,"maximum":120,"percent":100,"queue":0,"timestamp":"2022-03-17T06:27:29.000Z"},{"count":120,"maximum":120,"percent":100,"queue":0,"timestamp":"2022-03-17T06:39:39.000Z"},{"count":120,"maximum":120,"percent":100,"queue":0,"timestamp":"2022-03-17T06:51:55.000Z"}]