[{"count":72,"maximum":72,"percent":100,"queue":0,"timestamp":"2022-01-03T00:09:52.000Z"},{"count":72,"maximum":72,"percent":100,"queue":0,"timestamp":"2022-01-03T00:30:45.000Z"},{"count":72,"maximum":72,"percent":100,"queue":0,"timestamp":"2022-01-03T00:44:12.000Z"},{"count":72,"maximum":72,"percent":100,"queue":0,"timestamp":"2022-01-03T00:56:29.000Z"},{"count":72,"maximum":72,"percent":100,"queue":0,"timestamp":"2022-01-03T02:16:56.000Z"},{"count":72,"maximum":72,"percent":100,"queue":0,"timestamp":"2022-01-03T03:14:34.000Z"},{"count":72,"maximum":72,"percent":100,"queue":0,"timestamp":"2022-01-03T03:50:07.000Z"},{"count":72,"maximum":72,"percent":100,"queue":0,"timestamp":"2022-01-03T04:08:59.000Z"},{"count":72,"maximum":72,"percent":100,"queue":0,"timestamp":"2022-01-03T04:31:50.000Z"},{"count":72,"maximum":72,"percent":100,"queue":0,"timestamp":"2022-01-03T04:47:19.000Z"},{"count":72,"maximum":72,"percent":100,"queue":0,"timestamp":"2022-01-03T04:59:27.000Z"},{"count":72,"maximum":72,"percent":100,"queue":0,"timestamp":"2022-01-03T05:33:55.000Z"},{"count":72,"maximum":72,"percent":100,"queue":0,"timestamp":"2022-01-03T05:57:26.000Z"},{"count":72,"maximum":72,"percent":100,"queue":0,"timestamp":"2022-01-03T06:23:02.000Z"},{"count":72,"maximum":72,"percent":100,"queue":0,"timestamp":"2022-01-03T06:37:34.000Z"},{"count":72,"maximum":72,"percent":100,"queue":0,"timestamp":"2022-01-03T06:49:39.000Z"},{"count":72,"maximum":72,"percent":100,"queue":0,"timestamp":"2022-01-03T07:08:56.000Z"},{"count":72,"maximum":72,"percent":100,"queue":0,"timestamp":"2022-01-03T07:38:11.000Z"},{"count":72,"maximum":72,"percent":100,"queue":0,"timestamp":"2022-01-03T07:55:56.000Z"},{"count":72,"maximum":72,"percent":100,"queue":0,"timestamp":"2022-01-03T08:21:37.000Z"},{"count":72,"maximum":72,"percent":100,"queue":0,"timestamp":"2022-01-03T08:36:13.000Z"},{"count":72,"maximum":72,"percent":100,"queue":0,"timestamp":"2022-01-03T08:48:20.000Z"},{"count":72,"maximum":72,"percent":100,"queue":0,"timestamp":"2022-01-03T09:00:45.000Z"},{"count":72,"maximum":72,"percent":100,"queue":0,"timestamp":"2022-01-03T09:31:30.000Z"},{"count":72,"maximum":72,"percent":100,"queue":0,"timestamp":"2022-01-03T09:49:55.000Z"},{"count":72,"maximum":72,"percent":100,"queue":0,"timestamp":"2022-01-03T10:08:12.000Z"},{"count":72,"maximum":72,"percent":100,"queue":0,"timestamp":"2022-01-03T10:31:26.000Z"},{"count":72,"maximum":72,"percent":100,"queue":0,"timestamp":"2022-01-03T10:46:22.000Z"},{"count":72,"maximum":72,"percent":100,"queue":0,"timestamp":"2022-01-03T10:58:43.000Z"},{"count":72,"maximum":72,"percent":100,"queue":0,"timestamp":"2022-01-03T11:27:43.000Z"},{"count":72,"maximum":72,"percent":100,"queue":0,"timestamp":"2022-01-03T11:45:43.000Z"},{"count":72,"maximum":72,"percent":100,"queue":0,"timestamp":"2022-01-03T11:58:00.000Z"},{"count":72,"maximum":72,"percent":100,"queue":0,"timestamp":"2022-01-03T12:20:06.000Z"},{"count":72,"maximum":72,"percent":100,"queue":0,"timestamp":"2022-01-03T12:33:13.000Z"},{"count":72,"maximum":72,"percent":100,"queue":0,"timestamp":"2022-01-03T12:45:21.000Z"},{"count":72,"maximum":72,"percent":100,"queue":0,"timestamp":"2022-01-03T12:57:52.000Z"},{"count":72,"maximum":72,"percent":100,"queue":0,"timestamp":"2022-01-03T13:39:05.000Z"},{"count":3,"maximum":72,"percent":4,"queue":0,"timestamp":"2022-01-03T14:09:23.000Z"},{"count":-11,"maximum":72,"percent":-15,"queue":0,"timestamp":"2022-01-03T14:35:19.000Z"},{"count":-10,"maximum":72,"percent":-14,"queue":0,"timestamp":"2022-01-03T14:47:57.000Z"},{"count":-17,"maximum":72,"percent":-24,"queue":0,"timestamp":"2022-01-03T15:00:26.000Z"},{"count":-28,"maximum":72,"percent":-39,"queue":0,"timestamp":"2022-01-03T15:23:25.000Z"},{"count":-22,"maximum":72,"percent":-31,"queue":0,"timestamp":"2022-01-03T15:38:08.000Z"},{"count":-20,"maximum":72,"percent":-28,"queue":0,"timestamp":"2022-01-03T15:50:14.000Z"},{"count":-7,"maximum":72,"percent":-10,"queue":0,"timestamp":"2022-01-03T16:08:21.000Z"},{"count":1,"maximum":72,"percent":1,"queue":0,"timestamp":"2022-01-03T16:33:25.000Z"},{"count":3,"maximum":72,"percent":4,"queue":0,"timestamp":"2022-01-03T16:50:47.000Z"},{"count":-2,"maximum":72,"percent":-3,"queue":0,"timestamp":"2022-01-03T17:14:28.000Z"},{"count":11,"maximum":72,"percent":15,"queue":0,"timestamp":"2022-01-03T17:57:30.000Z"},{"count":26,"maximum":72,"percent":36,"queue":0,"timestamp":"2022-01-03T18:30:55.000Z"},{"count":32,"maximum":72,"percent":44,"queue":0,"timestamp":"2022-01-03T18:49:40.000Z"},{"count":26,"maximum":72,"percent":36,"queue":0,"timestamp":"2022-01-03T19:07:46.000Z"},{"count":33,"maximum":72,"percent":46,"queue":0,"timestamp":"2022-01-03T19:35:55.000Z"},{"count":37,"maximum":72,"percent":51,"queue":0,"timestamp":"2022-01-03T19:53:25.000Z"},{"count":37,"maximum":72,"percent":51,"queue":0,"timestamp":"2022-01-03T20:12:52.000Z"},{"count":40,"maximum":72,"percent":56,"queue":0,"timestamp":"2022-01-03T20:26:03.000Z"},{"count":40,"maximum":72,"percent":56,"queue":0,"timestamp":"2022-01-03T20:38:32.000Z"},{"count":41,"maximum":72,"percent":57,"queue":0,"timestamp":"2022-01-03T20:50:44.000Z"},{"count":46,"maximum":72,"percent":64,"queue":0,"timestamp":"2022-01-03T21:10:13.000Z"},{"count":47,"maximum":72,"percent":65,"queue":0,"timestamp":"2022-01-03T21:33:02.000Z"},{"count":48,"maximum":72,"percent":67,"queue":0,"timestamp":"2022-01-03T21:46:23.000Z"},{"count":54,"maximum":72,"percent":75,"queue":0,"timestamp":"2022-01-03T21:58:50.000Z"},{"count":57,"maximum":72,"percent":79,"queue":0,"timestamp":"2022-01-03T22:21:12.000Z"},{"count":57,"maximum":72,"percent":79,"queue":0,"timestamp":"2022-01-03T22:36:07.000Z"},{"count":57,"maximum":72,"percent":79,"queue":0,"timestamp":"2022-01-03T22:48:15.000Z"},{"count":57,"maximum":72,"percent":79,"queue":0,"timestamp":"2022-01-03T23:00:41.000Z"},{"count":57,"maximum":72,"percent":79,"queue":0,"timestamp":"2022-01-03T23:25:32.000Z"}]