[{"count":74,"maximum":150,"percent":49,"queue":0,"timestamp":"2021-07-16T00:09:19.000Z"},{"count":74,"maximum":150,"percent":49,"queue":0,"timestamp":"2021-07-16T00:30:25.000Z"},{"count":74,"maximum":150,"percent":49,"queue":0,"timestamp":"2021-07-16T00:42:50.000Z"},{"count":74,"maximum":150,"percent":49,"queue":0,"timestamp":"2021-07-16T00:55:07.000Z"},{"count":74,"maximum":150,"percent":49,"queue":0,"timestamp":"2021-07-16T01:18:45.000Z"},{"count":74,"maximum":150,"percent":49,"queue":0,"timestamp":"2021-07-16T01:32:54.000Z"},{"count":74,"maximum":150,"percent":49,"queue":0,"timestamp":"2021-07-16T01:45:10.000Z"},{"count":74,"maximum":150,"percent":49,"queue":0,"timestamp":"2021-07-16T01:57:33.000Z"},{"count":74,"maximum":150,"percent":49,"queue":0,"timestamp":"2021-07-16T03:11:42.000Z"},{"count":74,"maximum":150,"percent":49,"queue":0,"timestamp":"2021-07-16T04:09:44.000Z"},{"count":74,"maximum":150,"percent":49,"queue":0,"timestamp":"2021-07-16T04:38:52.000Z"},{"count":74,"maximum":150,"percent":49,"queue":0,"timestamp":"2021-07-16T04:51:42.000Z"},{"count":74,"maximum":150,"percent":49,"queue":0,"timestamp":"2021-07-16T05:11:46.000Z"},{"count":74,"maximum":150,"percent":49,"queue":0,"timestamp":"2021-07-16T05:34:51.000Z"},{"count":74,"maximum":150,"percent":49,"queue":0,"timestamp":"2021-07-16T05:49:14.000Z"},{"count":3,"maximum":150,"percent":2,"queue":0,"timestamp":"2021-07-16T06:05:29.000Z"},{"count":15,"maximum":150,"percent":10,"queue":0,"timestamp":"2021-07-16T06:37:29.000Z"},{"count":18,"maximum":150,"percent":12,"queue":0,"timestamp":"2021-07-16T06:56:28.000Z"},{"count":21,"maximum":150,"percent":14,"queue":0,"timestamp":"2021-07-16T07:18:42.000Z"},{"count":24,"maximum":150,"percent":16,"queue":0,"timestamp":"2021-07-16T07:30:54.000Z"},{"count":28,"maximum":150,"percent":19,"queue":0,"timestamp":"2021-07-16T07:43:09.000Z"},{"count":28,"maximum":150,"percent":19,"queue":0,"timestamp":"2021-07-16T07:55:18.000Z"},{"count":25,"maximum":150,"percent":17,"queue":0,"timestamp":"2021-07-16T08:25:05.000Z"},{"count":25,"maximum":150,"percent":17,"queue":0,"timestamp":"2021-07-16T08:51:53.000Z"},{"count":21,"maximum":150,"percent":14,"queue":0,"timestamp":"2021-07-16T09:09:56.000Z"},{"count":18,"maximum":150,"percent":12,"queue":0,"timestamp":"2021-07-16T09:27:28.000Z"},{"count":18,"maximum":150,"percent":12,"queue":0,"timestamp":"2021-07-16T09:39:39.000Z"},{"count":19,"maximum":150,"percent":13,"queue":0,"timestamp":"2021-07-16T09:51:52.000Z"},{"count":24,"maximum":150,"percent":16,"queue":0,"timestamp":"2021-07-16T10:13:06.000Z"}]