[{"count":74,"maximum":150,"percent":49,"queue":0,"timestamp":"2021-07-16T00:09:19.000Z"},{"count":74,"maximum":150,"percent":49,"queue":0,"timestamp":"2021-07-16T00:30:25.000Z"},{"count":74,"maximum":150,"percent":49,"queue":0,"timestamp":"2021-07-16T00:42:50.000Z"},{"count":74,"maximum":150,"percent":49,"queue":0,"timestamp":"2021-07-16T00:55:07.000Z"},{"count":74,"maximum":150,"percent":49,"queue":0,"timestamp":"2021-07-16T01:18:45.000Z"},{"count":74,"maximum":150,"percent":49,"queue":0,"timestamp":"2021-07-16T01:32:54.000Z"},{"count":74,"maximum":150,"percent":49,"queue":0,"timestamp":"2021-07-16T01:45:10.000Z"},{"count":74,"maximum":150,"percent":49,"queue":0,"timestamp":"2021-07-16T01:57:33.000Z"},{"count":74,"maximum":150,"percent":49,"queue":0,"timestamp":"2021-07-16T03:11:42.000Z"},{"count":74,"maximum":150,"percent":49,"queue":0,"timestamp":"2021-07-16T04:09:44.000Z"},{"count":74,"maximum":150,"percent":49,"queue":0,"timestamp":"2021-07-16T04:38:52.000Z"},{"count":74,"maximum":150,"percent":49,"queue":0,"timestamp":"2021-07-16T04:51:42.000Z"},{"count":74,"maximum":150,"percent":49,"queue":0,"timestamp":"2021-07-16T05:11:46.000Z"},{"count":74,"maximum":150,"percent":49,"queue":0,"timestamp":"2021-07-16T05:34:51.000Z"}]