[{"count":21,"maximum":150,"percent":14,"queue":0,"timestamp":"2021-09-13T00:08:02.000Z"},{"count":21,"maximum":150,"percent":14,"queue":0,"timestamp":"2021-09-13T00:27:10.000Z"},{"count":21,"maximum":150,"percent":14,"queue":0,"timestamp":"2021-09-13T00:40:35.000Z"},{"count":21,"maximum":150,"percent":14,"queue":0,"timestamp":"2021-09-13T00:52:58.000Z"},{"count":21,"maximum":150,"percent":14,"queue":0,"timestamp":"2021-09-13T01:13:19.000Z"},{"count":21,"maximum":150,"percent":14,"queue":0,"timestamp":"2021-09-13T01:30:26.000Z"},{"count":21,"maximum":150,"percent":14,"queue":0,"timestamp":"2021-09-13T01:42:42.000Z"},{"count":21,"maximum":150,"percent":14,"queue":0,"timestamp":"2021-09-13T01:54:54.000Z"},{"count":21,"maximum":150,"percent":14,"queue":0,"timestamp":"2021-09-13T03:02:12.000Z"},{"count":21,"maximum":150,"percent":14,"queue":0,"timestamp":"2021-09-13T04:04:35.000Z"},{"count":21,"maximum":150,"percent":14,"queue":0,"timestamp":"2021-09-13T04:35:38.000Z"},{"count":21,"maximum":150,"percent":14,"queue":0,"timestamp":"2021-09-13T04:50:36.000Z"},{"count":21,"maximum":150,"percent":14,"queue":0,"timestamp":"2021-09-13T05:08:31.000Z"},{"count":21,"maximum":150,"percent":14,"queue":0,"timestamp":"2021-09-13T05:29:29.000Z"},{"count":21,"maximum":150,"percent":14,"queue":0,"timestamp":"2021-09-13T05:44:04.000Z"},{"count":21,"maximum":150,"percent":14,"queue":0,"timestamp":"2021-09-13T05:56:10.000Z"},{"count":21,"maximum":150,"percent":14,"queue":0,"timestamp":"2021-09-13T06:28:33.000Z"},{"count":1,"maximum":150,"percent":1,"queue":0,"timestamp":"2021-09-13T06:53:23.000Z"},{"count":6,"maximum":150,"percent":4,"queue":0,"timestamp":"2021-09-13T07:12:45.000Z"},{"count":6,"maximum":150,"percent":4,"queue":0,"timestamp":"2021-09-13T07:27:49.000Z"},{"count":6,"maximum":150,"percent":4,"queue":0,"timestamp":"2021-09-13T07:39:57.000Z"},{"count":8,"maximum":150,"percent":5,"queue":0,"timestamp":"2021-09-13T07:52:20.000Z"},{"count":11,"maximum":150,"percent":7,"queue":0,"timestamp":"2021-09-13T08:14:38.000Z"},{"count":13,"maximum":150,"percent":9,"queue":0,"timestamp":"2021-09-13T08:39:44.000Z"},{"count":17,"maximum":150,"percent":11,"queue":0,"timestamp":"2021-09-13T08:54:04.000Z"},{"count":24,"maximum":150,"percent":16,"queue":0,"timestamp":"2021-09-13T09:16:03.000Z"},{"count":20,"maximum":150,"percent":13,"queue":0,"timestamp":"2021-09-13T09:30:35.000Z"},{"count":20,"maximum":150,"percent":13,"queue":0,"timestamp":"2021-09-13T09:42:50.000Z"},{"count":21,"maximum":150,"percent":14,"queue":0,"timestamp":"2021-09-13T09:55:11.000Z"},{"count":26,"maximum":150,"percent":17,"queue":0,"timestamp":"2021-09-13T10:22:17.000Z"},{"count":29,"maximum":150,"percent":19,"queue":0,"timestamp":"2021-09-13T10:40:03.000Z"},{"count":29,"maximum":150,"percent":19,"queue":0,"timestamp":"2021-09-13T10:52:19.000Z"},{"count":34,"maximum":150,"percent":23,"queue":0,"timestamp":"2021-09-13T11:12:11.000Z"},{"count":41,"maximum":150,"percent":27,"queue":0,"timestamp":"2021-09-13T11:31:09.000Z"},{"count":42,"maximum":150,"percent":28,"queue":0,"timestamp":"2021-09-13T11:44:13.000Z"},{"count":42,"maximum":150,"percent":28,"queue":0,"timestamp":"2021-09-13T11:57:09.000Z"},{"count":46,"maximum":150,"percent":31,"queue":0,"timestamp":"2021-09-13T12:24:49.000Z"},{"count":46,"maximum":150,"percent":31,"queue":0,"timestamp":"2021-09-13T12:42:20.000Z"},{"count":47,"maximum":150,"percent":31,"queue":0,"timestamp":"2021-09-13T12:54:28.000Z"},{"count":47,"maximum":150,"percent":31,"queue":0,"timestamp":"2021-09-13T13:14:19.000Z"},{"count":43,"maximum":150,"percent":29,"queue":0,"timestamp":"2021-09-13T13:27:52.000Z"},{"count":39,"maximum":150,"percent":26,"queue":0,"timestamp":"2021-09-13T13:40:04.000Z"},{"count":40,"maximum":150,"percent":27,"queue":0,"timestamp":"2021-09-13T13:52:30.000Z"},{"count":40,"maximum":150,"percent":27,"queue":0,"timestamp":"2021-09-13T14:21:43.000Z"},{"count":41,"maximum":150,"percent":27,"queue":0,"timestamp":"2021-09-13T14:59:16.000Z"},{"count":48,"maximum":150,"percent":32,"queue":0,"timestamp":"2021-09-13T15:29:54.000Z"},{"count":46,"maximum":150,"percent":31,"queue":0,"timestamp":"2021-09-13T15:44:15.000Z"},{"count":51,"maximum":150,"percent":34,"queue":0,"timestamp":"2021-09-13T15:56:21.000Z"},{"count":61,"maximum":150,"percent":41,"queue":0,"timestamp":"2021-09-13T16:19:52.000Z"},{"count":69,"maximum":150,"percent":46,"queue":0,"timestamp":"2021-09-13T16:33:32.000Z"},{"count":72,"maximum":150,"percent":48,"queue":0,"timestamp":"2021-09-13T16:49:08.000Z"},{"count":81,"maximum":150,"percent":54,"queue":0,"timestamp":"2021-09-13T16:58:07.000Z"},{"count":91,"maximum":150,"percent":61,"queue":0,"timestamp":"2021-09-13T17:24:07.000Z"},{"count":99,"maximum":150,"percent":66,"queue":0,"timestamp":"2021-09-13T17:43:18.000Z"},{"count":103,"maximum":150,"percent":69,"queue":0,"timestamp":"2021-09-13T17:55:29.000Z"},{"count":116,"maximum":150,"percent":77,"queue":0,"timestamp":"2021-09-13T18:29:31.000Z"},{"count":142,"maximum":150,"percent":95,"queue":0,"timestamp":"2021-09-13T19:01:44.000Z"},{"count":124,"maximum":150,"percent":83,"queue":0,"timestamp":"2021-09-13T19:26:01.000Z"},{"count":133,"maximum":150,"percent":89,"queue":0,"timestamp":"2021-09-13T19:41:47.000Z"},{"count":112,"maximum":150,"percent":75,"queue":0,"timestamp":"2021-09-13T19:54:18.000Z"},{"count":128,"maximum":150,"percent":85,"queue":0,"timestamp":"2021-09-13T20:20:22.000Z"},{"count":128,"maximum":150,"percent":85,"queue":0,"timestamp":"2021-09-13T20:41:56.000Z"},{"count":120,"maximum":150,"percent":80,"queue":0,"timestamp":"2021-09-13T20:54:04.000Z"},{"count":122,"maximum":150,"percent":81,"queue":0,"timestamp":"2021-09-13T21:13:11.000Z"},{"count":112,"maximum":150,"percent":75,"queue":0,"timestamp":"2021-09-13T21:25:33.000Z"},{"count":110,"maximum":150,"percent":73,"queue":0,"timestamp":"2021-09-13T21:37:43.000Z"}]