[{"count":65,"maximum":65,"percent":100,"queue":0,"timestamp":"2022-02-17T00:22:08.000Z"},{"count":65,"maximum":65,"percent":100,"queue":0,"timestamp":"2022-02-17T00:37:20.000Z"},{"count":65,"maximum":65,"percent":100,"queue":0,"timestamp":"2022-02-17T00:49:31.000Z"},{"count":65,"maximum":65,"percent":100,"queue":0,"timestamp":"2022-02-17T01:24:08.000Z"},{"count":65,"maximum":65,"percent":100,"queue":0,"timestamp":"2022-02-17T02:34:38.000Z"},{"count":65,"maximum":65,"percent":100,"queue":0,"timestamp":"2022-02-17T03:10:37.000Z"},{"count":65,"maximum":65,"percent":100,"queue":0,"timestamp":"2022-02-17T03:38:59.000Z"}]