[{"count":4,"maximum":416,"percent":1,"queue":0,"timestamp":"2021-08-25T00:21:33.000Z"},{"count":4,"maximum":416,"percent":1,"queue":0,"timestamp":"2021-08-25T00:34:30.000Z"},{"count":4,"maximum":416,"percent":1,"queue":0,"timestamp":"2021-08-25T00:46:45.000Z"},{"count":4,"maximum":416,"percent":1,"queue":0,"timestamp":"2021-08-25T00:58:55.000Z"},{"count":4,"maximum":416,"percent":1,"queue":0,"timestamp":"2021-08-25T01:22:33.000Z"},{"count":4,"maximum":416,"percent":1,"queue":0,"timestamp":"2021-08-25T01:36:53.000Z"},{"count":4,"maximum":416,"percent":1,"queue":0,"timestamp":"2021-08-25T01:49:03.000Z"},{"count":4,"maximum":416,"percent":1,"queue":0,"timestamp":"2021-08-25T02:16:56.000Z"},{"count":4,"maximum":416,"percent":1,"queue":0,"timestamp":"2021-08-25T03:28:30.000Z"},{"count":0,"maximum":416,"percent":0,"queue":0,"timestamp":"2021-08-25T04:09:10.000Z"},{"count":0,"maximum":416,"percent":0,"queue":0,"timestamp":"2021-08-25T04:37:06.000Z"},{"count":0,"maximum":416,"percent":0,"queue":0,"timestamp":"2021-08-25T04:50:03.000Z"},{"count":0,"maximum":416,"percent":0,"queue":0,"timestamp":"2021-08-25T05:07:23.000Z"},{"count":0,"maximum":416,"percent":0,"queue":0,"timestamp":"2021-08-25T05:29:27.000Z"},{"count":0,"maximum":416,"percent":0,"queue":0,"timestamp":"2021-08-25T05:44:42.000Z"},{"count":0,"maximum":416,"percent":0,"queue":0,"timestamp":"2021-08-25T05:56:49.000Z"},{"count":0,"maximum":416,"percent":0,"queue":0,"timestamp":"2021-08-25T06:29:04.000Z"},{"count":0,"maximum":416,"percent":0,"queue":0,"timestamp":"2021-08-25T06:53:36.000Z"},{"count":32,"maximum":416,"percent":8,"queue":0,"timestamp":"2021-08-25T07:13:09.000Z"},{"count":36,"maximum":416,"percent":9,"queue":0,"timestamp":"2021-08-25T07:27:46.000Z"},{"count":39,"maximum":416,"percent":9,"queue":0,"timestamp":"2021-08-25T07:39:56.000Z"},{"count":41,"maximum":416,"percent":10,"queue":0,"timestamp":"2021-08-25T07:52:20.000Z"},{"count":47,"maximum":416,"percent":11,"queue":0,"timestamp":"2021-08-25T08:14:39.000Z"},{"count":47,"maximum":416,"percent":11,"queue":0,"timestamp":"2021-08-25T08:40:08.000Z"},{"count":46,"maximum":416,"percent":11,"queue":0,"timestamp":"2021-08-25T08:54:34.000Z"},{"count":50,"maximum":416,"percent":12,"queue":0,"timestamp":"2021-08-25T09:16:53.000Z"},{"count":59,"maximum":416,"percent":14,"queue":0,"timestamp":"2021-08-25T09:30:25.000Z"},{"count":60,"maximum":416,"percent":14,"queue":0,"timestamp":"2021-08-25T09:42:36.000Z"},{"count":57,"maximum":416,"percent":14,"queue":0,"timestamp":"2021-08-25T09:55:04.000Z"},{"count":70,"maximum":416,"percent":17,"queue":0,"timestamp":"2021-08-25T10:21:15.000Z"},{"count":69,"maximum":416,"percent":17,"queue":0,"timestamp":"2021-08-25T10:38:48.000Z"},{"count":72,"maximum":416,"percent":17,"queue":0,"timestamp":"2021-08-25T10:50:58.000Z"},{"count":62,"maximum":416,"percent":15,"queue":0,"timestamp":"2021-08-25T11:08:54.000Z"},{"count":64,"maximum":416,"percent":15,"queue":0,"timestamp":"2021-08-25T11:29:15.000Z"},{"count":62,"maximum":416,"percent":15,"queue":0,"timestamp":"2021-08-25T11:43:24.000Z"},{"count":61,"maximum":416,"percent":15,"queue":0,"timestamp":"2021-08-25T11:55:38.000Z"},{"count":66,"maximum":416,"percent":16,"queue":0,"timestamp":"2021-08-25T12:23:39.000Z"},{"count":61,"maximum":416,"percent":15,"queue":0,"timestamp":"2021-08-25T12:41:33.000Z"},{"count":62,"maximum":416,"percent":15,"queue":0,"timestamp":"2021-08-25T12:53:42.000Z"},{"count":48,"maximum":416,"percent":12,"queue":0,"timestamp":"2021-08-25T13:12:28.000Z"},{"count":47,"maximum":416,"percent":11,"queue":0,"timestamp":"2021-08-25T13:26:48.000Z"},{"count":49,"maximum":416,"percent":12,"queue":0,"timestamp":"2021-08-25T13:39:02.000Z"},{"count":58,"maximum":416,"percent":14,"queue":0,"timestamp":"2021-08-25T13:51:26.000Z"},{"count":53,"maximum":416,"percent":13,"queue":0,"timestamp":"2021-08-25T14:15:37.000Z"},{"count":64,"maximum":416,"percent":15,"queue":0,"timestamp":"2021-08-25T14:51:04.000Z"},{"count":69,"maximum":416,"percent":17,"queue":0,"timestamp":"2021-08-25T15:20:26.000Z"},{"count":76,"maximum":416,"percent":18,"queue":0,"timestamp":"2021-08-25T15:38:01.000Z"},{"count":77,"maximum":416,"percent":19,"queue":0,"timestamp":"2021-08-25T15:46:23.000Z"},{"count":75,"maximum":416,"percent":18,"queue":0,"timestamp":"2021-08-25T15:58:28.000Z"},{"count":96,"maximum":416,"percent":23,"queue":0,"timestamp":"2021-08-25T16:20:37.000Z"},{"count":104,"maximum":416,"percent":25,"queue":0,"timestamp":"2021-08-25T16:33:50.000Z"},{"count":104,"maximum":416,"percent":25,"queue":0,"timestamp":"2021-08-25T16:46:02.000Z"},{"count":112,"maximum":416,"percent":27,"queue":0,"timestamp":"2021-08-25T16:58:17.000Z"},{"count":106,"maximum":416,"percent":25,"queue":0,"timestamp":"2021-08-25T17:22:44.000Z"},{"count":104,"maximum":416,"percent":25,"queue":0,"timestamp":"2021-08-25T17:37:44.000Z"},{"count":97,"maximum":416,"percent":23,"queue":0,"timestamp":"2021-08-25T17:50:12.000Z"},{"count":102,"maximum":416,"percent":25,"queue":0,"timestamp":"2021-08-25T18:10:23.000Z"},{"count":109,"maximum":416,"percent":26,"queue":0,"timestamp":"2021-08-25T18:51:25.000Z"},{"count":128,"maximum":416,"percent":31,"queue":0,"timestamp":"2021-08-25T19:16:32.000Z"},{"count":114,"maximum":416,"percent":27,"queue":0,"timestamp":"2021-08-25T19:38:12.000Z"},{"count":113,"maximum":416,"percent":27,"queue":0,"timestamp":"2021-08-25T19:50:19.000Z"},{"count":118,"maximum":416,"percent":28,"queue":0,"timestamp":"2021-08-25T20:08:21.000Z"},{"count":123,"maximum":416,"percent":30,"queue":0,"timestamp":"2021-08-25T20:34:21.000Z"},{"count":114,"maximum":416,"percent":27,"queue":0,"timestamp":"2021-08-25T20:50:56.000Z"},{"count":117,"maximum":416,"percent":28,"queue":0,"timestamp":"2021-08-25T21:07:31.000Z"},{"count":97,"maximum":416,"percent":23,"queue":0,"timestamp":"2021-08-25T21:21:07.000Z"},{"count":85,"maximum":416,"percent":20,"queue":0,"timestamp":"2021-08-25T21:33:34.000Z"},{"count":61,"maximum":416,"percent":15,"queue":0,"timestamp":"2021-08-25T21:45:59.000Z"},{"count":46,"maximum":416,"percent":11,"queue":0,"timestamp":"2021-08-25T21:58:17.000Z"},{"count":29,"maximum":416,"percent":7,"queue":0,"timestamp":"2021-08-25T22:23:12.000Z"},{"count":22,"maximum":416,"percent":5,"queue":0,"timestamp":"2021-08-25T22:37:51.000Z"},{"count":16,"maximum":416,"percent":4,"queue":0,"timestamp":"2021-08-25T22:50:02.000Z"},{"count":10,"maximum":416,"percent":2,"queue":0,"timestamp":"2021-08-25T23:06:11.000Z"},{"count":10,"maximum":416,"percent":2,"queue":0,"timestamp":"2021-08-25T23:25:40.000Z"},{"count":10,"maximum":416,"percent":2,"queue":0,"timestamp":"2021-08-25T23:39:39.000Z"},{"count":10,"maximum":416,"percent":2,"queue":0,"timestamp":"2021-08-25T23:52:05.000Z"}]