[{"count":33,"maximum":416,"percent":8,"queue":0,"timestamp":"2021-08-12T00:22:50.000Z"},{"count":33,"maximum":416,"percent":8,"queue":0,"timestamp":"2021-08-12T00:38:43.000Z"},{"count":33,"maximum":416,"percent":8,"queue":0,"timestamp":"2021-08-12T00:51:21.000Z"},{"count":33,"maximum":416,"percent":8,"queue":0,"timestamp":"2021-08-12T01:09:48.000Z"},{"count":33,"maximum":416,"percent":8,"queue":0,"timestamp":"2021-08-12T01:28:48.000Z"},{"count":33,"maximum":416,"percent":8,"queue":0,"timestamp":"2021-08-12T01:41:18.000Z"},{"count":33,"maximum":416,"percent":8,"queue":0,"timestamp":"2021-08-12T01:53:44.000Z"},{"count":33,"maximum":416,"percent":8,"queue":0,"timestamp":"2021-08-12T02:50:02.000Z"},{"count":33,"maximum":416,"percent":8,"queue":0,"timestamp":"2021-08-12T03:49:04.000Z"},{"count":0,"maximum":416,"percent":0,"queue":0,"timestamp":"2021-08-12T04:16:22.000Z"},{"count":0,"maximum":416,"percent":0,"queue":0,"timestamp":"2021-08-12T04:40:59.000Z"},{"count":0,"maximum":416,"percent":0,"queue":0,"timestamp":"2021-08-12T04:53:06.000Z"},{"count":0,"maximum":416,"percent":0,"queue":0,"timestamp":"2021-08-12T05:15:26.000Z"},{"count":0,"maximum":416,"percent":0,"queue":0,"timestamp":"2021-08-12T05:35:51.000Z"},{"count":0,"maximum":416,"percent":0,"queue":0,"timestamp":"2021-08-12T05:48:49.000Z"},{"count":0,"maximum":416,"percent":0,"queue":0,"timestamp":"2021-08-12T06:03:22.000Z"},{"count":0,"maximum":416,"percent":0,"queue":0,"timestamp":"2021-08-12T06:34:40.000Z"},{"count":0,"maximum":416,"percent":0,"queue":0,"timestamp":"2021-08-12T06:55:12.000Z"},{"count":13,"maximum":416,"percent":3,"queue":0,"timestamp":"2021-08-12T07:16:21.000Z"},{"count":17,"maximum":416,"percent":4,"queue":0,"timestamp":"2021-08-12T07:29:09.000Z"},{"count":20,"maximum":416,"percent":5,"queue":0,"timestamp":"2021-08-12T07:41:26.000Z"},{"count":25,"maximum":416,"percent":6,"queue":0,"timestamp":"2021-08-12T07:54:02.000Z"},{"count":24,"maximum":416,"percent":6,"queue":0,"timestamp":"2021-08-12T08:20:38.000Z"},{"count":29,"maximum":416,"percent":7,"queue":0,"timestamp":"2021-08-12T08:46:08.000Z"},{"count":42,"maximum":416,"percent":10,"queue":0,"timestamp":"2021-08-12T08:58:14.000Z"},{"count":45,"maximum":416,"percent":11,"queue":0,"timestamp":"2021-08-12T09:20:10.000Z"}]